Workbook

Sheet 📊 Dashboard
A1: VIVID CRM — SQA MASTER TEST TRACKER | Banking Sector | Multi-Tenant
A2: ISO/IEC 25010 Aligned | Date: 10-Jun-2026 | Version: 1.0
A4: TEST AREA | B4: TOTAL | C4: PASS | D4: FAIL | E4: WARN | F4: PASS RATE
A5: 01 — Authentication | B5: =COUNTIF('🧪 Results'!B:B,"*SA-*") | C5: =COUNTIFS('🧪 Results'!B:B,"*SA-*",'🧪 Results'!E:E,"PASS") | D5: =COUNTIFS('🧪 Results'!B:B,"*SA-*",'🧪 Results'!E:E,"FAIL") | E5: =COUNTIFS('🧪 Results'!B:B,"*SA-*",'🧪 Results'!E:E,"WARN") | F5: =IFERROR(TEXT(C5/B5,"0.0%"),"-")
A6: 02 — Tenant Provisioning | B6: =COUNTIF('🧪 Results'!B:B,"*SA-*") | C6: =COUNTIFS('🧪 Results'!B:B,"*SA-*",'🧪 Results'!E:E,"PASS") | D6: =COUNTIFS('🧪 Results'!B:B,"*SA-*",'🧪 Results'!E:E,"FAIL") | E6: =COUNTIFS('🧪 Results'!B:B,"*SA-*",'🧪 Results'!E:E,"WARN") | F6: =IFERROR(TEXT(C6/B6,"0.0%"),"-")
A7: 03 — User Hierarchy (Admin) | B7: =COUNTIF('🧪 Results'!B:B,"*TA-*") | C7: =COUNTIFS('🧪 Results'!B:B,"*TA-*",'🧪 Results'!E:E,"PASS") | D7: =COUNTIFS('🧪 Results'!B:B,"*TA-*",'🧪 Results'!E:E,"FAIL") | E7: =COUNTIFS('🧪 Results'!B:B,"*TA-*",'🧪 Results'!E:E,"WARN") | F7: =IFERROR(TEXT(C7/B7,"0.0%"),"-")
A8: 04 — RBAC & Visibility | B8: =COUNTIF('🧪 Results'!B:B,"*RB-*") | C8: =COUNTIFS('🧪 Results'!B:B,"*RB-*",'🧪 Results'!E:E,"PASS") | D8: =COUNTIFS('🧪 Results'!B:B,"*RB-*",'🧪 Results'!E:E,"FAIL") | E8: =COUNTIFS('🧪 Results'!B:B,"*RB-*",'🧪 Results'!E:E,"WARN") | F8: =IFERROR(TEXT(C8/B8,"0.0%"),"-")
A9: 05 — Contacts Module | B9: =COUNTIF('🧪 Results'!B:B,"*M01*") | C9: =COUNTIFS('🧪 Results'!B:B,"*M01*",'🧪 Results'!E:E,"PASS") | D9: =COUNTIFS('🧪 Results'!B:B,"*M01*",'🧪 Results'!E:E,"FAIL") | E9: =COUNTIFS('🧪 Results'!B:B,"*M01*",'🧪 Results'!E:E,"WARN") | F9: =IFERROR(TEXT(C9/B9,"0.0%"),"-")
A10: 06 — Deals & Pipelines | B10: =COUNTIF('🧪 Results'!B:B,"*M03*") | C10: =COUNTIFS('🧪 Results'!B:B,"*M03*",'🧪 Results'!E:E,"PASS") | D10: =COUNTIFS('🧪 Results'!B:B,"*M03*",'🧪 Results'!E:E,"FAIL") | E10: =COUNTIFS('🧪 Results'!B:B,"*M03*",'🧪 Results'!E:E,"WARN") | F10: =IFERROR(TEXT(C10/B10,"0.0%"),"-")
A11: 07 — Activities | B11: =COUNTIF('🧪 Results'!B:B,"*M04*") | C11: =COUNTIFS('🧪 Results'!B:B,"*M04*",'🧪 Results'!E:E,"PASS") | D11: =COUNTIFS('🧪 Results'!B:B,"*M04*",'🧪 Results'!E:E,"FAIL") | E11: =COUNTIFS('🧪 Results'!B:B,"*M04*",'🧪 Results'!E:E,"WARN") | F11: =IFERROR(TEXT(C11/B11,"0.0%"),"-")
A12: 08 — Tickets & Help Desk | B12: =COUNTIF('🧪 Results'!B:B,"*M05*") | C12: =COUNTIFS('🧪 Results'!B:B,"*M05*",'🧪 Results'!E:E,"PASS") | D12: =COUNTIFS('🧪 Results'!B:B,"*M05*",'🧪 Results'!E:E,"FAIL") | E12: =COUNTIFS('🧪 Results'!B:B,"*M05*",'🧪 Results'!E:E,"WARN") | F12: =IFERROR(TEXT(C12/B12,"0.0%"),"-")
A13: 09 — CSAT & Audit Log | B13: =COUNTIF('🧪 Results'!B:B,"*M06*") | C13: =COUNTIFS('🧪 Results'!B:B,"*M06*",'🧪 Results'!E:E,"PASS") | D13: =COUNTIFS('🧪 Results'!B:B,"*M06*",'🧪 Results'!E:E,"FAIL") | E13: =COUNTIFS('🧪 Results'!B:B,"*M06*",'🧪 Results'!E:E,"WARN") | F13: =IFERROR(TEXT(C13/B13,"0.0%"),"-")
A14: 10 — Analytics | B14: =COUNTIF('🧪 Results'!B:B,"*M07*") | C14: =COUNTIFS('🧪 Results'!B:B,"*M07*",'🧪 Results'!E:E,"PASS") | D14: =COUNTIFS('🧪 Results'!B:B,"*M07*",'🧪 Results'!E:E,"FAIL") | E14: =COUNTIFS('🧪 Results'!B:B,"*M07*",'🧪 Results'!E:E,"WARN") | F14: =IFERROR(TEXT(C14/B14,"0.0%"),"-")
A15: 11 — Sales & Invoicing | B15: =COUNTIF('🧪 Results'!B:B,"*M08*") | C15: =COUNTIFS('🧪 Results'!B:B,"*M08*",'🧪 Results'!E:E,"PASS") | D15: =COUNTIFS('🧪 Results'!B:B,"*M08*",'🧪 Results'!E:E,"FAIL") | E15: =COUNTIFS('🧪 Results'!B:B,"*M08*",'🧪 Results'!E:E,"WARN") | F15: =IFERROR(TEXT(C15/B15,"0.0%"),"-")
A16: 12 — Security (OWASP) | B16: =COUNTIF('🧪 Results'!B:B,"*SEC*") | C16: =COUNTIFS('🧪 Results'!B:B,"*SEC*",'🧪 Results'!E:E,"PASS") | D16: =COUNTIFS('🧪 Results'!B:B,"*SEC*",'🧪 Results'!E:E,"FAIL") | E16: =COUNTIFS('🧪 Results'!B:B,"*SEC*",'🧪 Results'!E:E,"WARN") | F16: =IFERROR(TEXT(C16/B16,"0.0%"),"-")
A17: 13 — UI/UX Quality | B17: =COUNTIF('🧪 Results'!B:B,"*UX-*") | C17: =COUNTIFS('🧪 Results'!B:B,"*UX-*",'🧪 Results'!E:E,"PASS") | D17: =COUNTIFS('🧪 Results'!B:B,"*UX-*",'🧪 Results'!E:E,"FAIL") | E17: =COUNTIFS('🧪 Results'!B:B,"*UX-*",'🧪 Results'!E:E,"WARN") | F17: =IFERROR(TEXT(C17/B17,"0.0%"),"-")
A18: 14 — Cross-Tenant Isolation | B18: =COUNTIF('🧪 Results'!B:B,"*RB-0*") | C18: =COUNTIFS('🧪 Results'!B:B,"*RB-0*",'🧪 Results'!E:E,"PASS") | D18: =COUNTIFS('🧪 Results'!B:B,"*RB-0*",'🧪 Results'!E:E,"FAIL") | E18: =COUNTIFS('🧪 Results'!B:B,"*RB-0*",'🧪 Results'!E:E,"WARN") | F18: =IFERROR(TEXT(C18/B18,"0.0%"),"-")
A19: TOTALS | B19: =SUM(B5:B18) | C19: =SUM(C5:C18) | D19: =SUM(D5:D18) | E19: =SUM(E5:E18) | F19: =IFERROR(TEXT(C19/B19,"0.0%"),"-")
A21: STATUS LEGEND
A22: ✓ PASS
A23: ✗ FAIL
A24: ⚠ WARN
A25: ⏭ SKIP
A26: 🔄 IN PROGRESS

Sheet 🧪 Results
A1: # | B1: TC ID | C1: Test Case Description | D1: Pre-Condition | E1: Status | F1: Expected Result | G1: Actual Result | H1: Tester | I1: Date Executed
A2: 1 | B2: SA-01 | C2: Super Admin login with valid credentials | D2: API running, super admin seeded | F2: 200 OK, JWT token returned | H2: SQA-Agent-01
A3: 2 | B3: SA-02 | C3: JWT contains role=super_admin claim | D3: SA-01 passed | F3: JWT payload.role = super_admin | H3: SQA-Agent-01
A4: 3 | B4: SA-03 | C4: JWT contains tenantId claim | D4: SA-01 passed | F4: tenantId claim present in JWT | H4: SQA-Agent-01
A5: 4 | B5: SA-04 | C5: Wrong password returns 401 | D5: Valid user exists | F5: HTTP 401 Unauthorized | H5: SQA-Agent-01
A6: 5 | B6: SA-05 | C6: Login without tenantSlug returns 400 | D6: API running | F6: HTTP 400 Bad Request | H6: SQA-Agent-01
A7: 6 | B7: SA-06 | C7: Super admin can list all tenants | D7: SA-01 passed | F7: 200 OK, array of tenants with user_count | H7: SQA-Agent-01
A8: 7 | B8: SA-07 | C8: Tenant list includes usage meta (user_count) | D8: SA-06 passed | F8: user_count present on each tenant | H8: SQA-Agent-01
A9: 8 | B9: SA-08 | C9: Module catalog returns all 7 modules | D9: SA-01 passed | F9: 7 modules, crm always=true | H9: SQA-Agent-01
A10: 9 | B10: SA-09 | C10: Create Alpha Bank (banking sector) | D10: SA-01 passed | F10: 201 Created, tenant seeded with banking fields | H10: SQA-Agent-01
A11: 10 | B11: SA-10 | C11: Super admin upgrades Alpha Bank plan to professional | D11: SA-09 passed | F11: 200 OK, plan=professional | H11: SQA-Agent-01
A12: 11 | B12: SA-11 | C12: Enable CRM+Ticketing+Analytics+Emails modules for Alpha Bank | D12: SA-09 passed | F12: 200 OK, active_modules updated | H12: SQA-Agent-01
A13: 12 | B13: SA-12 | C13: Create Beta Bank (banking sector, starter plan) | D13: SA-01 passed | F13: 201 Created | H13: SQA-Agent-01
... A136: 135 | B136: UX-10 | C136: CORS headers present (OPTIONS responds) | D136: API running | F136: No 500 on OPTIONS | H136: SQA-Agent-05

Sheet 🐛 Defect Log
A1: Defect # | B1: TC ID | C1: Defect Description | D1: Severity | E1: Priority | F1: Steps to Reproduce | G1: Status | H1: Assigned To | I1: Date Found | J1: Date Fixed

Sheet 📋 Execution Log
A1: Run # | B1: Agent | C1: Run Date | D1: Environment | E1: Total | F1: Passed | G1: Pass % | H1: Notes

Sheet 📦 Test Data
A1: VIVID CRM — SQA TEST DATA REFERENCE
A2: CATEGORY | B2: VALUE | C2: NOTES
A3: ── SERVICES ─────────────────────────────────────────────────────────────────
A4: API Base URL | B4: http://localhost:3000 | C4: Dev environment
A5: Frontend URL | B5: http://localhost:5173 | C5: Vite dev server
A6: Swagger Docs | B6: http://localhost:3000/docs | C6: OpenAPI UI
A7: DB Connection | B7: postgresql://crm:crm_dev_password@localhost:5432/crm_platform | C7: Dev DB
A8: ── SUPER ADMIN ──────────────────────────────────────────────────────────────
A9: Super Admin Email | B9: admin@demo.com | C9: In demo workspace
A10: Super Admin Password | B10: Vivid@Solutions1 | C10: Default dev credentials
A11: Super Admin Slug | B11: demo | C11: Banking sector workspace
A12: ── ALPHA BANK (Full-featured) ───────────────────────────────────────────────
A13: Slug | B13: sqa-alpha-bank | C13: Banking sector, Professional plan
A14: Admin Email | B14: admin@alpha-bank-sqa.com | C14: Created by SQA Agent 01
A15: Admin Password | B15: Admin@Alpha2026! | C15: Test credential
A16: Modules | B16: crm, ticketing, analytics, emails | C16: Licensed by super admin
A17: ── BETA BANK (Limited) ──────────────────────────────────────────────────────
A18: Slug | B18: sqa-beta-bank | C18: Banking sector, Starter plan
A19: Admin Email | B19: admin@beta-bank-sqa.com | C19: Created by SQA Agent 01
A20: Admin Password | B20: Admin@Beta2026! | C20: Test credential
A21: Modules | B21: crm, ticketing | C21: Starter plan limitation
A22: ── TEST USERS (same password for all) ─────────────────────────────────────
A23: Test Password | B23: Test@CRM2026! | C23: All invited users
A24: Retail Manager | B24: mgr.retail.[alpha|beta]@sqa-vivid.com | C24: role=manager
A25: Retail Asst Mgr | B25: am.retail.[alpha|beta]@sqa-vivid.com | C25: role=agent
A26: Retail Executive | B26: exec.retail.[alpha|beta]@sqa-vivid.com | C26: role=agent
A27: Loans Manager | B27: mgr.loans.[alpha|beta]@sqa-vivid.com | C27: role=manager
A28: Support Manager | B28: mgr.support.[alpha|beta]@sqa-vivid.com | C28: role=manager
A29: Support Agent 1 | B29: agent1.support.[alpha|beta]@sqa-vivid.com | C29: role=agent
A30: Compliance Viewer | B30: viewer.compliance.[alpha|beta]@sqa-vivid.com | C30: role=viewer
A31: ── PASSWORD POLICY ─────────────────────────────────────────────────────────
A32: Min Length | B32: 10 characters | C32: BCRYPT cost 14
A33: Requirements | B33: Upper + Lower + Digit + Special | C33: Enterprise policy
A34: Lockout | B34: 5 failed attempts → 15min lockout | C34: Redis-backed
